{
    "_id" : "push_productQualityMasterData",
    "version" : "V2",
    "componentType" : "ChainedSystemTask",
    "object" : "ae5f314e-c377-419e-9dfa-1f296f6fccfa",
    "objectAction" : "CREATE",
    "taskId" : "push_productQualityMasterData",
    "refType" : "app",
    "refTypeId" : "12325a98-a959-4939-9005-4158d136afcd",
    "type" : "workflow",
    "tags" : "notifyDataChange",    
    "chainedTasks" : [ 
		{
            "name" : "_ST_CREATE_PRODUCT_QUALITY_MASTER_DATA",
            "appendMsg" : false,
            "data" : "output.push_productQualityMasterData"
        }
    ]
}