{
  "_id" : "sellingOptions_propertyKey",
  "type" : "property",
  "name" : "sellingoptions_property",
  "propertyLevel" : "app",
  "dataType" : "String",
  "fieldType" : "textbox",
  "length" : "20",
  "defaultValue" : [ 
      {
          "key" : "Contract",
          "value" : "Contract",
          "class" : "radio-card",
          "description" : "Allocate to a Cargill or third-party contract"
      }, 
      {
          "key" : "Cash",
          "value" : "Cash",
          "class" : "radio-card",
          "description" : "Allocate to a cash bid"
      }, 
      {
          "key" : "Pool",
          "value" : "Pool",
          "class" : "radio-card",
          "description" : "Allocate to a pool"
      }
  ],
  "label" : "Selling option",
  "refTypeId" : "12325a98-a959-4939-9005-4158d136afcd",
  "description" : "Contract, cash or pool"
}